CONTRIBUTORS.rst
HISTORY.rst
LICENSE
MANIFEST.in
README.rst
setup.cfg
setup.py
tox.ini
hyper/__init__.py
hyper/certs.pem
hyper/cli.py
hyper/compat.py
hyper/contrib.py
hyper/httplib_compat.py
hyper/ssl_compat.py
hyper/tls.py
hyper/common/__init__.py
hyper/common/bufsocket.py
hyper/common/connection.py
hyper/common/decoder.py
hyper/common/exceptions.py
hyper/common/headers.py
hyper/common/util.py
hyper/http11/__init__.py
hyper/http11/connection.py
hyper/http11/parser.py
hyper/http11/response.py
hyper/http20/__init__.py
hyper/http20/connection.py
hyper/http20/errors.py
hyper/http20/exceptions.py
hyper/http20/response.py
hyper/http20/stream.py
hyper/http20/util.py
hyper/http20/window.py
hyper_joinup.egg-info/PKG-INFO
hyper_joinup.egg-info/SOURCES.txt
hyper_joinup.egg-info/dependency_links.txt
hyper_joinup.egg-info/entry_points.txt
hyper_joinup.egg-info/requires.txt
hyper_joinup.egg-info/top_level.txt
test/server.py
test/test_SSLContext.py
test/test_abstraction.py
test/test_cli.py
test/test_headers.py
test/test_http11.py
test/test_http20.py
test/test_hyper.py
test/test_hyper_SSLContext.py
test/test_import.py
test/test_integration.py
test/test_integration_http11.py
test/test_parser.py
test/test_socket.py
test/test_ssl_socket.py
test/test_windowmanager.py
test/certs/client.crt
test/certs/client.key
test/certs/nopassword.pem
test/certs/server.crt
test/certs/server.key