Metadata-Version: 2.1
Name: hyper-joinup
Version: 0.8.0
Summary: HTTP/2 Client for Python
Home-page: http://hyper.rtfd.org
Author: Cory Benfield
Author-email: cory@lukasa.co.uk
License: MIT License
Platform: UNKNOWN
Classifier: Development Status :: 3 - Alpha
Classifier: Intended Audience :: Developers
Classifier: License :: OSI Approved :: MIT License
Classifier: Programming Language :: Python
Classifier: Programming Language :: Python :: 2
Classifier: Programming Language :: Python :: 2.7
Classifier: Programming Language :: Python :: 3
Classifier: Programming Language :: Python :: 3.4
Classifier: Programming Language :: Python :: 3.5
Classifier: Programming Language :: Python :: Implementation :: CPython
Provides-Extra: fast
